{
    "keep": {
        "days": true,
        "amount": 30
    },
    "auditLog": "log/.85db1fd5f3263409fb63939cc049ec762040a72f-audit.json",
    "files": [
        {
            "date": 1620906700514,
            "name": "log/2021-05-13-17-results.log",
            "hash": "3701c3ff34729ce4de0ea37f85585582"
        },
        {
            "date": 1620912744033,
            "name": "log/2021-05-13-19-results.log",
            "hash": "8d385b5d81aba90fb1a2844a2b596527"
        },
        {
            "date": 1620916329932,
            "name": "log/2021-05-13-20-results.log",
            "hash": "93c9e64d8e5bf1f649c32413b1d3367d"
        },
        {
            "date": 1620919840809,
            "name": "log/2021-05-13-21-results.log",
            "hash": "b69159fd519c9a7cadbec8b210d96254"
        }
    ]
}